bakm/__init__.py
bakm/__main__.py
bakm/bitwarden.py
bakm/cli.py
bakm/config.py
bakm/core.py
bakm/models.py
bitwardnaikeymanager-0.1.0.dist-info/METADATA
bitwardnaikeymanager-0.1.0.dist-info/WHEEL
bitwardnaikeymanager-0.1.0.dist-info/entry_points.txt
bitwardnaikeymanager-0.1.0.dist-info/top_level.txt
bitwardnaikeymanager-0.1.0.dist-info/RECORD
