Metadata-Version: 2.4
Name: bitwardnaikeymanager
Version: 0.1.0
Summary: Use AI to manage your Bitwarden API keys.
Requires-Python: >=3.9
Requires-Dist: pydantic>=2.11.7
Requires-Dist: python-dotenv>=1.1.1
Requires-Dist: pyyaml>=6.0.2
Requires-Dist: typer>=0.16.0
